{
"type": "FeatureCollection",
"name": "BCNSPP",
"crs": { "type": "name", "properties": { "name": "urn:ogc:def:crs:OGC:1.3:CRS84" } },
"features": [
{ "type": "Feature", "properties": { "RCID": 112, "PRIM": 1, "GRUP": 2, "OBJL": 9, "RVER": 1, "AGEN": 550, "FIDN": 945801558, "FIDS": 2030, "LNAM": "0226385FC95607EE", "LNAM_REFS": [ "02262FDE213707EE" ], "FFPT_RIND": [ 2 ], "BCNSHP": 1, "CATSPM": "27", "COLOUR": "", "OBJNAM": "Avalon Jetty Light A", "STATUS": "8", "SCAMIN": 89999, "SORDAT": "20201124", "SORIND": "US,US,reprt,5thCGD,LNM 47\/20" }, "geometry": { "type": "Point", "coordinates": [ -74.7034639, 39.1067389 ] } }
]
}
