{
"type": "FeatureCollection",
"name": "SILTNK",
"crs": { "type": "name", "properties": { "name": "urn:ogc:def:crs:OGC:1.3:CRS84" } },
"features": [
{ "type": "Feature", "properties": { "RCID": 1138, "PRIM": 1, "GRUP": 2, "OBJL": 125, "RVER": 1, "AGEN": 550, "FIDN": 36924771, "FIDS": 50, "LNAM": "022602336D630032", "CATSIL": 4, "CONVIS": 1, "PRODCT": "3", "SCAMIN": 89999, "SORDAT": "20170406", "SORIND": "US,US,graph,Chart 12316" }, "geometry": { "type": "Point", "coordinates": [ -74.8135089, 38.9925203 ] } },
{ "type": "Feature", "properties": { "RCID": 1139, "PRIM": 1, "GRUP": 2, "OBJL": 125, "RVER": 1, "AGEN": 550, "FIDN": 36963019, "FIDS": 50, "LNAM": "0226023402CB0032", "CATSIL": 2, "CONVIS": 1, "SCAMIN": 89999, "SORDAT": "200512", "SORIND": "US,US,graph,Chart 12316" }, "geometry": { "type": "Point", "coordinates": [ -74.6919813, 39.1575609 ] } },
{ "type": "Feature", "properties": { "RCID": 1140, "PRIM": 1, "GRUP": 2, "OBJL": 125, "RVER": 1, "AGEN": 550, "FIDN": 36963648, "FIDS": 50, "LNAM": "0226023405400032", "CATSIL": 2, "CONVIS": 1, "SCAMIN": 89999, "SORDAT": "20170406", "SORIND": "US,US,graph,Chart 12316" }, "geometry": { "type": "Point", "coordinates": [ -74.6273436, 39.2370941 ] } },
{ "type": "Feature", "properties": { "RCID": 1141, "PRIM": 1, "GRUP": 2, "OBJL": 125, "RVER": 1, "AGEN": 550, "FIDN": 36963012, "FIDS": 50, "LNAM": "0226023402C40032", "CATSIL": 2, "CONVIS": 1, "SCAMIN": 89999, "SORDAT": "200512", "SORIND": "US,US,graph,Chart 12316" }, "geometry": { "type": "Point", "coordinates": [ -74.7121469, 39.130213 ] } },
{ "type": "Feature", "properties": { "RCID": 1142, "PRIM": 1, "GRUP": 2, "OBJL": 125, "RVER": 1, "AGEN": 550, "FIDN": 36963017, "FIDS": 50, "LNAM": "0226023402C90032", "CATSIL": 2, "CONVIS": 1, "SCAMIN": 89999, "SORDAT": "200512", "SORIND": "US,US,graph,Chart 12316" }, "geometry": { "type": "Point", "coordinates": [ -74.6572729, 39.197571 ] } },
{ "type": "Feature", "properties": { "RCID": 1143, "PRIM": 1, "GRUP": 2, "OBJL": 125, "RVER": 1, "AGEN": 550, "FIDN": 36926358, "FIDS": 50, "LNAM": "0226023373960032", "CATSIL": 2, "CONVIS": 1, "SCAMIN": 89999, "SORDAT": "200512", "SORIND": "US,US,graph,Chart 12316" }, "geometry": { "type": "Point", "coordinates": [ -74.8282913, 39.0830297 ] } },
{ "type": "Feature", "properties": { "RCID": 1144, "PRIM": 1, "GRUP": 2, "OBJL": 125, "RVER": 1, "AGEN": 550, "FIDN": 36926351, "FIDS": 50, "LNAM": "02260233738F0032", "CATSIL": 2, "CONVIS": 1, "SCAMIN": 89999, "SORDAT": "200512", "SORIND": "US,US,graph,Chart 12316" }, "geometry": { "type": "Point", "coordinates": [ -74.7277136, 39.0907 ] } },
{ "type": "Feature", "properties": { "RCID": 1145, "PRIM": 1, "GRUP": 2, "OBJL": 125, "RVER": 1, "AGEN": 550, "FIDN": 36926355, "FIDS": 50, "LNAM": "0226023373930032", "CATSIL": 2, "CONVIS": 1, "SCAMIN": 89999, "SORDAT": "200512", "SORIND": "US,US,graph,Chart 12316" }, "geometry": { "type": "Point", "coordinates": [ -74.8171837, 38.9890438 ] } },
{ "type": "Feature", "properties": { "RCID": 1146, "PRIM": 1, "GRUP": 2, "OBJL": 125, "RVER": 1, "AGEN": 550, "FIDN": 36926335, "FIDS": 50, "LNAM": "02260233737F0032", "CATSIL": 4, "CONVIS": 1, "PRODCT": "3", "SCAMIN": 89999, "SORDAT": "200512", "SORIND": "US,US,graph,Chart 12316" }, "geometry": { "type": "Point", "coordinates": [ -74.8390774, 38.9741033 ] } },
{ "type": "Feature", "properties": { "RCID": 1147, "PRIM": 1, "GRUP": 2, "OBJL": 125, "RVER": 1, "AGEN": 550, "FIDN": 36926336, "FIDS": 50, "LNAM": "0226023373800032", "CATSIL": 2, "CONVIS": 1, "SCAMIN": 89999, "SORDAT": "200512", "SORIND": "US,US,graph,Chart 12316" }, "geometry": { "type": "Point", "coordinates": [ -74.7588589, 39.0542498 ] } },
{ "type": "Feature", "properties": { "RCID": 1148, "PRIM": 1, "GRUP": 2, "OBJL": 125, "RVER": 1, "AGEN": 550, "FIDN": 36926341, "FIDS": 50, "LNAM": "0226023373850032", "CATSIL": 4, "CONVIS": 1, "PRODCT": "3", "SCAMIN": 89999, "SORDAT": "200512", "SORIND": "US,US,graph,Chart 12316" }, "geometry": { "type": "Point", "coordinates": [ -74.7965345, 39.0051737 ] } },
{ "type": "Feature", "properties": { "RCID": 1149, "PRIM": 1, "GRUP": 2, "OBJL": 125, "RVER": 1, "AGEN": 550, "FIDN": 36963641, "FIDS": 50, "LNAM": "0226023405390032", "CATSIL": 2, "CONVIS": 1, "SCAMIN": 89999, "SORDAT": "20170406", "SORIND": "US,US,graph,Chart 12316" }, "geometry": { "type": "Point", "coordinates": [ -74.7136546, 39.1063914 ] } }
]
}
