{
"type": "FeatureCollection",
"name": "UWTROC",
"crs": { "type": "name", "properties": { "name": "urn:ogc:def:crs:OGC:1.3:CRS84" } },
"features": [
{ "type": "Feature", "properties": { "RCID": 1217, "PRIM": 1, "GRUP": 2, "OBJL": 153, "RVER": 1, "AGEN": 550, "FIDN": 36962866, "FIDS": 50, "LNAM": "0226023402320032", "QUASOU": "2", "WATLEV": 4, "SORDAT": "200512", "SORIND": "US,US,graph,Chart 12316" }, "geometry": { "type": "Point", "coordinates": [ -74.7109469, 39.1136351 ] } },
{ "type": "Feature", "properties": { "RCID": 1218, "PRIM": 1, "GRUP": 2, "OBJL": 153, "RVER": 1, "AGEN": 550, "FIDN": 36962869, "FIDS": 50, "LNAM": "0226023402350032", "QUASOU": "2", "WATLEV": 4, "SORDAT": "200512", "SORIND": "US,US,graph,Chart 12316" }, "geometry": { "type": "Point", "coordinates": [ -74.7114645, 39.1134209 ] } }
]
}
