{
"type": "FeatureCollection",
"name": "MORFAC",
"crs": { "type": "name", "properties": { "name": "urn:ogc:def:crs:OGC:1.3:CRS84" } },
"features": [
{ "type": "Feature", "properties": { "RCID": 8637, "PRIM": 1, "GRUP": 2, "OBJL": 84, "RVER": 1, "AGEN": 550, "FIDN": 36983944, "FIDS": 50, "LNAM": "0226023454880032", "CATMOR": 1, "WATLEV": 2, "SCAMIN": 59999, "SORDAT": "20170406", "SORIND": "US,US,graph,Chart 12316" }, "geometry": { "type": "Point", "coordinates": [ -74.6283804, 39.2527493 ] } }
]
}
