{
"type": "FeatureCollection",
"name": "CGUSTA",
"crs": { "type": "name", "properties": { "name": "urn:ogc:def:crs:OGC:1.3:CRS84" } },
"features": [
{ "type": "Feature", "properties": { "RCID": 1709, "PRIM": 1, "GRUP": 2, "OBJL": 29, "RVER": 1, "AGEN": 550, "FIDN": 37005443, "FIDS": 50, "LNAM": "02260234A8830032", "SCAMIN": 21999, "SORDAT": "20050600", "SORIND": "US,US,graph,Chart 12318" }, "geometry": { "type": "Point", "coordinates": [ -74.423149, 39.3783368 ] } }
]
}
